kaisergradient/__init__.py
kaisergradient/gradient.py
kaisergadient-0.0.101.dist-info/METADATA
kaisergadient-0.0.101.dist-info/WHEEL
kaisergadient-0.0.101.dist-info/top_level.txt
kaisergadient-0.0.101.dist-info/RECORD
