Metadata-Version: 2.1
Name: kaisergadient
Version: 0.0.101
Summary: Easy and simple Gradient
Author: Kaiser Fechner
Author-email: <coolpotatorocks@gmail.com>
Keywords: python,gradient,simple
Classifier: Development Status :: 1 - Planning
Classifier: Intended Audience :: Developers
Classifier: Programming Language :: Python :: 3
Classifier: Operating System :: Unix
Classifier: Operating System :: MacOS :: MacOS X
Classifier: Operating System :: Microsoft :: Windows
